devtools_unix_perms/__init__.py
devtools_unix_perms-1.0.1.dist-info/METADATA
devtools_unix_perms-1.0.1.dist-info/WHEEL
devtools_unix_perms-1.0.1.dist-info/top_level.txt
devtools_unix_perms-1.0.1.dist-info/RECORD
