Metadata-Version: 2.1
Name: devtools-unix-perms
Version: 1.0.1
Summary: Unix permissions calculator
Home-page: https://devtools.at/tools/unix-permissions
Author: DevTools.at
Author-email: hello@devtools.at
Project-URL: Homepage, https://devtools.at/tools/unix-permissions
Project-URL: Repository, https://github.com/devtools-at/unix-permissions
Classifier: Development Status :: 4 - Beta
Classifier: Intended Audience :: Developers
Classifier: License :: OSI Approved :: MIT License
Classifier: Programming Language :: Python :: 3
Requires-Python: >=3.8
